setup.cfg
setup.py
cabot_alert_irc/__init__.py
cabot_alert_irc/models.py
cabot_alert_irc.egg-info/PKG-INFO
cabot_alert_irc.egg-info/SOURCES.txt
cabot_alert_irc.egg-info/dependency_links.txt
cabot_alert_irc.egg-info/requires.txt
cabot_alert_irc.egg-info/top_level.txt