Metadata-Version: 1.0
Name: cabot-alert-irc
Version: 1.1.0
Summary: An IRC alert plugin for Cabot by Arachnys
Home-page: http://cabotapp.com
Author: nobe4
Author-email: vh@nobe4.fr
License: MIT
Platform: UNKNOWN
